mkdocs_word_filter/__init__.py
mkdocs_word_filter/plugin.py
mkdocs_word_filter-0.1.1.dist-info/METADATA
mkdocs_word_filter-0.1.1.dist-info/RECORD
mkdocs_word_filter-0.1.1.dist-info/WHEEL
mkdocs_word_filter-0.1.1.dist-info/entry_points.txt
mkdocs_word_filter-0.1.1.dist-info/top_level.txt
