Metadata-Version: 2.1
Name: mkdocs-word-filter
Version: 0.1.1
Summary: A MkDocs plugin to filter extra content that was to markdown documents for e.g. formatting docx files.
Home-page: https://github.com/miikama/mkdocs-word-filter
Author: Miika Mäkelä
Author-email: makelanmiika@gmail.com
License: MIT
Keywords: mkdocs markdown word filter
Platform: UNKNOWN
Classifier: License :: OSI Approved :: MIT License
Classifier: Programming Language :: Python
Classifier: Programming Language :: Python :: 3 :: Only
Classifier: Programming Language :: Python :: 3.5
Classifier: Programming Language :: Python :: 3.6
Classifier: Programming Language :: Python :: 3.7
Requires-Python: >=3.5
Requires-Dist: mkdocs
